{"cameraMode":{"drawMode":0,"name":"Shaded","section":"Shading Mode"},"sceneLighting":false,"audioPlay":false,"sceneViewState":{"m_AlwaysRefresh":false,"showFog":true,"showSkybox":false,"showFlares":true,"showImageEffects":true,"showParticleSystems":true,"showVisualEffectGraphs":true,"m_FxEnabled":true},"in2DMode":false,"pivot":{"x":18.5096492767334,"y":12.095680236816407,"z":-23.252334594726564},"rotation":{"x":-0.10513122379779816,"y":0.14742526412010194,"z":-0.015730177983641626,"w":-0.9833692312240601},"size":12.12435531616211,"orthographic":false}